certcc_ssvc-2025.10.101215.dist-info/licenses/LICENSE
ssvc/__init__.py
ssvc/_mixins.py
ssvc/_version.py
ssvc/csv_analyzer.py
ssvc/doc_helpers.py
ssvc/doctools.py
ssvc/md_gen.py
ssvc/namespaces.py
ssvc/policy_generator.py
ssvc/registry_demo.py
ssvc/selection.py
ssvc/api/__init__.py
ssvc/api/helpers.py
ssvc/api/main.py
ssvc/api/v1/__init__.py
ssvc/api/v1/response_models/__init__.py
ssvc/api/v1/response_models/_type_defs.py
ssvc/api/v1/routers/__init__.py
ssvc/api/v1/routers/decision_point.py
ssvc/api/v1/routers/decision_points.py
ssvc/api/v1/routers/decision_table.py
ssvc/api/v1/routers/decision_tables.py
ssvc/api/v1/routers/keys.py
ssvc/api/v1/routers/namespaces.py
ssvc/api/v1/routers/objects.py
ssvc/api/v1/routers/types.py
ssvc/api/v1/routers/v1_router.py
ssvc/api/v1/routers/versions.py
ssvc/decision_points/__init__.py
ssvc/decision_points/base.py
ssvc/decision_points/helpers.py
ssvc/decision_points/basic/__init__.py
ssvc/decision_points/basic/base.py
ssvc/decision_points/basic/near_boundary.py
ssvc/decision_points/basic/probability/__init__.py
ssvc/decision_points/basic/probability/cis_wep.py
ssvc/decision_points/basic/probability/five_equal.py
ssvc/decision_points/basic/probability/five_weighted.py
ssvc/decision_points/basic/probability/two_equal.py
ssvc/decision_points/basic/quantiles/__init__.py
ssvc/decision_points/basic/quantiles/median.py
ssvc/decision_points/basic/quantiles/quartiles.py
ssvc/decision_points/basic/quantiles/quintiles.py
ssvc/decision_points/cisa/__init__.py
ssvc/decision_points/cisa/base.py
ssvc/decision_points/cisa/in_kev.py
ssvc/decision_points/cisa/mission_prevalence.py
ssvc/decision_points/cvss/__init__.py
ssvc/decision_points/cvss/_not_defined.py
ssvc/decision_points/cvss/attack_complexity.py
ssvc/decision_points/cvss/attack_requirements.py
ssvc/decision_points/cvss/attack_vector.py
ssvc/decision_points/cvss/authentication.py
ssvc/decision_points/cvss/availability_impact.py
ssvc/decision_points/cvss/availability_requirement.py
ssvc/decision_points/cvss/base.py
certcc_ssvc-2025.10.101215.dist-info/METADATA
certcc_ssvc-2025.10.101215.dist-info/WHEEL
certcc_ssvc-2025.10.101215.dist-info/entry_points.txt
certcc_ssvc-2025.10.101215.dist-info/top_level.txt
certcc_ssvc-2025.10.101215.dist-info/RECORD
