Metadata-Version: 2.4
Name: certcc-ssvc
Version: 2025.10.101215
Summary: Tools for working with a Stakeholder Specific Vulnerability Categorization (SSVC)
Author-email: CERT/CC SSVC <cert+ssvc@cert.org>
Project-URL: Homepage, https://certcc.github.io/SSVC
Project-URL: Project, https://github.com/CERTCC/SSVC
Project-URL: Bug Tracker, https://github.com/CERTCC/SSVC/issues
Keywords: ssvc,vulnerability management,vulnerability management
Classifier: Development Status :: 4 - Beta
Classifier: Programming Language :: Python :: 3
Classifier: Topic :: Security
Classifier: Topic :: Software Development :: Libraries :: Python Modules
Requires-Python: >=3.12
License-File: LICENSE
Requires-Dist: mkdocs>=1.6.1
Requires-Dist: mkdocs-material>=9.6.18
Requires-Dist: mkdocs-material-extensions>=1.3.1
Requires-Dist: mkdocstrings>=0.30.0
Requires-Dist: mkdocstrings-python>=1.17.0
Requires-Dist: mkdocs-include-markdown-plugin>=7.1.8
Requires-Dist: pandas>=2.3.2
Requires-Dist: scipy>=1.16.1
Requires-Dist: jsonschema>=4.25.1
Requires-Dist: mkdocs-bibtex>=4.4.0
Requires-Dist: mkdocs-table-reader-plugin>=3.1.0
Requires-Dist: mkdocs-print-site-plugin>=2.8
Requires-Dist: markdown-exec[ansi]>=1.11.0
Requires-Dist: thefuzz>=0.22.1
Requires-Dist: scikit-learn>=1.6.1
Requires-Dist: networkx>=3.4.2
Requires-Dist: pydantic>=2.11.7
Requires-Dist: semver>=3.0.4
Requires-Dist: fastapi[all,standard]>=0.116.1
Dynamic: license-file
